{
    "metrics": {
        "retrieval": [
            0.6764705882352942,
            0.6764705882352942
        ],
        "prediction": [],
        "scoring": [
            0.1657848324514991,
            0.15123456790123455,
            0.13209876543209875,
            0.13209876543209875,
            0.1657848324514991,
            0.1703703703703704,
            0.15648148148148147,
            0.11296296296296297,
            0.1657848324514991,
            0.08765432098765433,
            0.08774250440917107,
            0.1037477954144621,
            0.1657848324514991,
            0.304320987654321,
            0.3148148148148148,
            0.36975308641975313,
            0.1657848324514991,
            0.3108465608465608,
            0.32962962962962966,
            0.3765432098765431,
            0.1657848324514991,
            0.2713403880070547,
            0.354320987654321,
            0.3771604938271605,
            0.1657848324514991,
            0.3016460905349794,
            0.32222222222222224,
            0.2858024691358025,
            0.1657848324514991,
            0.32195767195767194,
            0.2935626102292768,
            0.38183421516754845,
            0.1657848324514991,
            0.1657848324514991,
            0.1657848324514991,
            0.13806584362139918,
            0.162037037037037,
            0.1657848324514991,
            0.13991769547325103,
            0.17201646090534978,
            0.1657848324514991,
            0.1277777777777778,
            0.15925925925925924,
            0.1657848324514991,
            0.2552910052910053
        ],
        "regexp": []
    },
    "configs": {
        "regexp": [],
        "retrieval": [
            {
                "module_type": "vector_db",
                "module_params": {
                    "k": 10,
                    "embedder_name": "avsolatorio/GIST-small-Embedding-v0"
                },
                "metric_name": "retrieval_hit_rate",
                "metric_value": 0.6764705882352942,
                "module_dump_dir": null
            },
            {
                "module_type": "vector_db",
                "module_params": {
                    "k": 10,
                    "embedder_name": "infgrad/stella-base-en-v2"
                },
                "metric_name": "retrieval_hit_rate",
                "metric_value": 0.6764705882352942,
                "module_dump_dir": null
            }
        ],
        "scoring": [
            {
                "module_type": "dnnc",
                "module_params": {
                    "cross_encoder_name": "cross-encoder/ms-marco-MiniLM-L-6-v2",
                    "train_head": true,
                    "k": 1
                },
                "metric_name": "scoring_f1",
                "metric_value": 0.1657848324514991,
                "module_dump_dir": null
            },
            {
                "module_type": "dnnc",
                "module_params": {
                    "cross_encoder_name": "cross-encoder/ms-marco-MiniLM-L-6-v2",
                    "train_head": true,
                    "k": 3
                },
                "metric_name": "scoring_f1",
                "metric_value": 0.15123456790123455,
                "module_dump_dir": null
            },
            {
                "module_type": "dnnc",
                "module_params": {
                    "cross_encoder_name": "cross-encoder/ms-marco-MiniLM-L-6-v2",
                    "train_head": true,
                    "k": 5
                },
                "metric_name": "scoring_f1",
                "metric_value": 0.13209876543209875,
                "module_dump_dir": null
            },
            {
                "module_type": "dnnc",
                "module_params": {
                    "cross_encoder_name": "cross-encoder/ms-marco-MiniLM-L-6-v2",
                    "train_head": true,
                    "k": 10
                },
                "metric_name": "scoring_f1",
                "metric_value": 0.13209876543209875,
                "module_dump_dir": null
            },
            {
                "module_type": "dnnc",
                "module_params": {
                    "cross_encoder_name": "cross-encoder/ms-marco-MiniLM-L-4-v2",
                    "train_head": true,
                    "k": 1
                },
                "metric_name": "scoring_f1",
                "metric_value": 0.1657848324514991,
                "module_dump_dir": null
            },
            {
                "module_type": "dnnc",
                "module_params": {
                    "cross_encoder_name": "cross-encoder/ms-marco-MiniLM-L-4-v2",
                    "train_head": true,
                    "k": 3
                },
                "metric_name": "scoring_f1",
                "metric_value": 0.1703703703703704,
                "module_dump_dir": null
            },
            {
                "module_type": "dnnc",
                "module_params": {
                    "cross_encoder_name": "cross-encoder/ms-marco-MiniLM-L-4-v2",
                    "train_head": true,
                    "k": 5
                },
                "metric_name": "scoring_f1",
                "metric_value": 0.15648148148148147,
                "module_dump_dir": null
            },
            {
                "module_type": "dnnc",
                "module_params": {
                    "cross_encoder_name": "cross-encoder/ms-marco-MiniLM-L-4-v2",
                    "train_head": true,
                    "k": 10
                },
                "metric_name": "scoring_f1",
                "metric_value": 0.11296296296296297,
                "module_dump_dir": null
            },
            {
                "module_type": "dnnc",
                "module_params": {
                    "cross_encoder_name": "cross-encoder/ms-marco-MiniLM-L-12-v2",
                    "train_head": true,
                    "k": 1
                },
                "metric_name": "scoring_f1",
                "metric_value": 0.1657848324514991,
                "module_dump_dir": null
            },
            {
                "module_type": "dnnc",
                "module_params": {
                    "cross_encoder_name": "cross-encoder/ms-marco-MiniLM-L-12-v2",
                    "train_head": true,
                    "k": 3
                },
                "metric_name": "scoring_f1",
                "metric_value": 0.08765432098765433,
                "module_dump_dir": null
            },
            {
                "module_type": "dnnc",
                "module_params": {
                    "cross_encoder_name": "cross-encoder/ms-marco-MiniLM-L-12-v2",
                    "train_head": true,
                    "k": 5
                },
                "metric_name": "scoring_f1",
                "metric_value": 0.08774250440917107,
                "module_dump_dir": null
            },
            {
                "module_type": "dnnc",
                "module_params": {
                    "cross_encoder_name": "cross-encoder/ms-marco-MiniLM-L-12-v2",
                    "train_head": true,
                    "k": 10
                },
                "metric_name": "scoring_f1",
                "metric_value": 0.1037477954144621,
                "module_dump_dir": null
            },
            {
                "module_type": "dnnc",
                "module_params": {
                    "cross_encoder_name": "intfloat/multilingual-e5-large-instruct",
                    "train_head": true,
                    "k": 1
                },
                "metric_name": "scoring_f1",
                "metric_value": 0.1657848324514991,
                "module_dump_dir": null
            },
            {
                "module_type": "dnnc",
                "module_params": {
                    "cross_encoder_name": "intfloat/multilingual-e5-large-instruct",
                    "train_head": true,
                    "k": 3
                },
                "metric_name": "scoring_f1",
                "metric_value": 0.304320987654321,
                "module_dump_dir": null
            },
            {
                "module_type": "dnnc",
                "module_params": {
                    "cross_encoder_name": "intfloat/multilingual-e5-large-instruct",
                    "train_head": true,
                    "k": 5
                },
                "metric_name": "scoring_f1",
                "metric_value": 0.3148148148148148,
                "module_dump_dir": null
            },
            {
                "module_type": "dnnc",
                "module_params": {
                    "cross_encoder_name": "intfloat/multilingual-e5-large-instruct",
                    "train_head": true,
                    "k": 10
                },
                "metric_name": "scoring_f1",
                "metric_value": 0.36975308641975313,
                "module_dump_dir": null
            },
            {
                "module_type": "dnnc",
                "module_params": {
                    "cross_encoder_name": "deepvk/USER-bge-m3",
                    "train_head": true,
                    "k": 1
                },
                "metric_name": "scoring_f1",
                "metric_value": 0.1657848324514991,
                "module_dump_dir": null
            },
            {
                "module_type": "dnnc",
                "module_params": {
                    "cross_encoder_name": "deepvk/USER-bge-m3",
                    "train_head": true,
                    "k": 3
                },
                "metric_name": "scoring_f1",
                "metric_value": 0.3108465608465608,
                "module_dump_dir": null
            },
            {
                "module_type": "dnnc",
                "module_params": {
                    "cross_encoder_name": "deepvk/USER-bge-m3",
                    "train_head": true,
                    "k": 5
                },
                "metric_name": "scoring_f1",
                "metric_value": 0.32962962962962966,
                "module_dump_dir": null
            },
            {
                "module_type": "dnnc",
                "module_params": {
                    "cross_encoder_name": "deepvk/USER-bge-m3",
                    "train_head": true,
                    "k": 10
                },
                "metric_name": "scoring_f1",
                "metric_value": 0.3765432098765431,
                "module_dump_dir": null
            },
            {
                "module_type": "dnnc",
                "module_params": {
                    "cross_encoder_name": "BAAI/bge-m3",
                    "train_head": true,
                    "k": 1
                },
                "metric_name": "scoring_f1",
                "metric_value": 0.1657848324514991,
                "module_dump_dir": null
            },
            {
                "module_type": "dnnc",
                "module_params": {
                    "cross_encoder_name": "BAAI/bge-m3",
                    "train_head": true,
                    "k": 3
                },
                "metric_name": "scoring_f1",
                "metric_value": 0.2713403880070547,
                "module_dump_dir": null
            },
            {
                "module_type": "dnnc",
                "module_params": {
                    "cross_encoder_name": "BAAI/bge-m3",
                    "train_head": true,
                    "k": 5
                },
                "metric_name": "scoring_f1",
                "metric_value": 0.354320987654321,
                "module_dump_dir": null
            },
            {
                "module_type": "dnnc",
                "module_params": {
                    "cross_encoder_name": "BAAI/bge-m3",
                    "train_head": true,
                    "k": 10
                },
                "metric_name": "scoring_f1",
                "metric_value": 0.3771604938271605,
                "module_dump_dir": null
            },
            {
                "module_type": "dnnc",
                "module_params": {
                    "cross_encoder_name": "ai-forever/ru-en-RoSBERTa",
                    "train_head": true,
                    "k": 1
                },
                "metric_name": "scoring_f1",
                "metric_value": 0.1657848324514991,
                "module_dump_dir": null
            },
            {
                "module_type": "dnnc",
                "module_params": {
                    "cross_encoder_name": "ai-forever/ru-en-RoSBERTa",
                    "train_head": true,
                    "k": 3
                },
                "metric_name": "scoring_f1",
                "metric_value": 0.3016460905349794,
                "module_dump_dir": null
            },
            {
                "module_type": "dnnc",
                "module_params": {
                    "cross_encoder_name": "ai-forever/ru-en-RoSBERTa",
                    "train_head": true,
                    "k": 5
                },
                "metric_name": "scoring_f1",
                "metric_value": 0.32222222222222224,
                "module_dump_dir": null
            },
            {
                "module_type": "dnnc",
                "module_params": {
                    "cross_encoder_name": "ai-forever/ru-en-RoSBERTa",
                    "train_head": true,
                    "k": 10
                },
                "metric_name": "scoring_f1",
                "metric_value": 0.2858024691358025,
                "module_dump_dir": null
            },
            {
                "module_type": "dnnc",
                "module_params": {
                    "cross_encoder_name": "BAAI/bge-reranker-base",
                    "train_head": true,
                    "k": 1
                },
                "metric_name": "scoring_f1",
                "metric_value": 0.1657848324514991,
                "module_dump_dir": null
            },
            {
                "module_type": "dnnc",
                "module_params": {
                    "cross_encoder_name": "BAAI/bge-reranker-base",
                    "train_head": true,
                    "k": 3
                },
                "metric_name": "scoring_f1",
                "metric_value": 0.32195767195767194,
                "module_dump_dir": null
            },
            {
                "module_type": "dnnc",
                "module_params": {
                    "cross_encoder_name": "BAAI/bge-reranker-base",
                    "train_head": true,
                    "k": 5
                },
                "metric_name": "scoring_f1",
                "metric_value": 0.2935626102292768,
                "module_dump_dir": null
            },
            {
                "module_type": "dnnc",
                "module_params": {
                    "cross_encoder_name": "BAAI/bge-reranker-base",
                    "train_head": true,
                    "k": 10
                },
                "metric_name": "scoring_f1",
                "metric_value": 0.38183421516754845,
                "module_dump_dir": null
            },
            {
                "module_type": "knn",
                "module_params": {
                    "k": 1,
                    "weights": "uniform",
                    "embedder_name": "avsolatorio/GIST-small-Embedding-v0"
                },
                "metric_name": "scoring_f1",
                "metric_value": 0.1657848324514991,
                "module_dump_dir": null
            },
            {
                "module_type": "knn",
                "module_params": {
                    "k": 1,
                    "weights": "distance",
                    "embedder_name": "avsolatorio/GIST-small-Embedding-v0"
                },
                "metric_name": "scoring_f1",
                "metric_value": 0.1657848324514991,
                "module_dump_dir": null
            },
            {
                "module_type": "knn",
                "module_params": {
                    "k": 1,
                    "weights": "closest",
                    "embedder_name": "avsolatorio/GIST-small-Embedding-v0"
                },
                "metric_name": "scoring_f1",
                "metric_value": 0.1657848324514991,
                "module_dump_dir": null
            },
            {
                "module_type": "knn",
                "module_params": {
                    "k": 3,
                    "weights": "uniform",
                    "embedder_name": "avsolatorio/GIST-small-Embedding-v0"
                },
                "metric_name": "scoring_f1",
                "metric_value": 0.13806584362139918,
                "module_dump_dir": null
            },
            {
                "module_type": "knn",
                "module_params": {
                    "k": 3,
                    "weights": "distance",
                    "embedder_name": "avsolatorio/GIST-small-Embedding-v0"
                },
                "metric_name": "scoring_f1",
                "metric_value": 0.162037037037037,
                "module_dump_dir": null
            },
            {
                "module_type": "knn",
                "module_params": {
                    "k": 3,
                    "weights": "closest",
                    "embedder_name": "avsolatorio/GIST-small-Embedding-v0"
                },
                "metric_name": "scoring_f1",
                "metric_value": 0.1657848324514991,
                "module_dump_dir": null
            },
            {
                "module_type": "knn",
                "module_params": {
                    "k": 5,
                    "weights": "uniform",
                    "embedder_name": "avsolatorio/GIST-small-Embedding-v0"
                },
                "metric_name": "scoring_f1",
                "metric_value": 0.13991769547325103,
                "module_dump_dir": null
            },
            {
                "module_type": "knn",
                "module_params": {
                    "k": 5,
                    "weights": "distance",
                    "embedder_name": "avsolatorio/GIST-small-Embedding-v0"
                },
                "metric_name": "scoring_f1",
                "metric_value": 0.17201646090534978,
                "module_dump_dir": null
            },
            {
                "module_type": "knn",
                "module_params": {
                    "k": 5,
                    "weights": "closest",
                    "embedder_name": "avsolatorio/GIST-small-Embedding-v0"
                },
                "metric_name": "scoring_f1",
                "metric_value": 0.1657848324514991,
                "module_dump_dir": null
            },
            {
                "module_type": "knn",
                "module_params": {
                    "k": 10,
                    "weights": "uniform",
                    "embedder_name": "avsolatorio/GIST-small-Embedding-v0"
                },
                "metric_name": "scoring_f1",
                "metric_value": 0.1277777777777778,
                "module_dump_dir": null
            },
            {
                "module_type": "knn",
                "module_params": {
                    "k": 10,
                    "weights": "distance",
                    "embedder_name": "avsolatorio/GIST-small-Embedding-v0"
                },
                "metric_name": "scoring_f1",
                "metric_value": 0.15925925925925924,
                "module_dump_dir": null
            },
            {
                "module_type": "knn",
                "module_params": {
                    "k": 10,
                    "weights": "closest",
                    "embedder_name": "avsolatorio/GIST-small-Embedding-v0"
                },
                "metric_name": "scoring_f1",
                "metric_value": 0.1657848324514991,
                "module_dump_dir": null
            },
            {
                "module_type": "linear",
                "module_params": {
                    "embedder_name": "avsolatorio/GIST-small-Embedding-v0"
                },
                "metric_name": "scoring_f1",
                "metric_value": 0.2552910052910053,
                "module_dump_dir": null
            }
        ],
        "prediction": []
    }
}
